aibone-0.0.1.dist-info/licenses/LICENSE
automata/Alphabet.py
automata/TG.py
automata/__init__.py
aibone-0.0.1.dist-info/METADATA
aibone-0.0.1.dist-info/WHEEL
aibone-0.0.1.dist-info/top_level.txt
aibone-0.0.1.dist-info/RECORD
