Metadata-Version: 2.4
Name: aibone
Version: 0.0.1
Summary: A Python package for handling theory of automata in artificial intelligence.
Home-page: https://github.com/CortexNexus/aibone
Author: Aqsa Kashif
Author-email: aqsa.gogreen@gmail.com
Classifier: Programming Language :: Python :: 3
Classifier: Operating System :: OS Independent
Requires-Python: >=3.6
License-File: LICENSE
Dynamic: author
Dynamic: author-email
Dynamic: classifier
Dynamic: description
Dynamic: description-content-type
Dynamic: home-page
Dynamic: license-file
Dynamic: requires-python
Dynamic: summary
